swarmauri_keyprovider_pkcs11/Pkcs11KeyProvider.py
swarmauri_keyprovider_pkcs11/__init__.py
swarmauri_keyprovider_pkcs11-0.3.0.dev5.dist-info/LICENSE
swarmauri_keyprovider_pkcs11-0.3.0.dev5.dist-info/METADATA
swarmauri_keyprovider_pkcs11-0.3.0.dev5.dist-info/WHEEL
swarmauri_keyprovider_pkcs11-0.3.0.dev5.dist-info/entry_points.txt
swarmauri_keyprovider_pkcs11-0.3.0.dev5.dist-info/RECORD
